memorizer/__about__.py
memorizer/__init__.py
memorizer-0.0.1.dist-info/METADATA
memorizer-0.0.1.dist-info/WHEEL
memorizer-0.0.1.dist-info/licenses/LICENSE.txt
memorizer-0.0.1.dist-info/RECORD
